ml/__init__.py
ml/evaluator.py
ml/model_factory.py
ml/trainer.py
ml/algorithms/__init__.py
ml/algorithms/base.py
ml/algorithms/catboost_model.py
ml/algorithms/lightgbm_model.py
ml/algorithms/random_forest_model.py
ml/algorithms/sklearn_models.py
ml/algorithms/xgboost_model.py
ml/preprocessing/__init__.py
ml/preprocessing/pipeline_builder.py
ml/preprocessing/pipeline_executor.py
ml/preprocessing/pipeline_registry.py
ml/preprocessing/analyzers/__init__.py
ml/preprocessing/analyzers/data_analyzer.py
ml/preprocessing/analyzers/recommendation.py
ml/preprocessing/analyzers/stats_calculator.py
ml/preprocessing/cleaners/__init__.py
ml/preprocessing/cleaners/base.py
ml/preprocessing/cleaners/duplicate_handler.py
ml/preprocessing/cleaners/missing_handler.py
ml/preprocessing/cleaners/outlier_handler.py
ml/preprocessing/cleaners/type_converter.py
ml/preprocessing/engineers/__init__.py
ml/preprocessing/engineers/aggregator.py
ml/preprocessing/engineers/base.py
ml/preprocessing/engineers/date_engineer.py
ml/preprocessing/engineers/formula_engine.py
ml/preprocessing/processors/__init__.py
ml/preprocessing/processors/base.py
ml/preprocessing/processors/categorical_encoder.py
ml/preprocessing/processors/feature_selector.py
ml/preprocessing/processors/numerical_scaler.py
ml/test/__init__.py
ml/test/test_imports.py
ml/test/test_ml_package.py
ml/test/test_pipeline_steps.py
willaya_ml2-1.0.0.dist-info/licenses/LICENSE
willaya_ml2-1.0.0.dist-info/METADATA
willaya_ml2-1.0.0.dist-info/WHEEL
willaya_ml2-1.0.0.dist-info/top_level.txt
willaya_ml2-1.0.0.dist-info/RECORD
