Metadata-Version: 2.4
Name: willaya-ml2
Version: 1.0.0
Summary: An enterprise-grade AutoML and Pipeline orchestration library for 2p AI.
Author-email: Mohamed Elsayed <mabdelmotgally@2p.com>
License: WILLAYA PRIVATE SOFTWARE LICENSE AGREEMENT
Requires-Python: >=3.9
License-File: LICENSE
Requires-Dist: pandas>=2.0.0
Requires-Dist: scikit-learn>=1.3.0
Requires-Dist: optuna>=3.4.0
Requires-Dist: xgboost>=2.0.0
Requires-Dist: lightgbm>=4.1.0
Requires-Dist: catboost>=1.2.0
Requires-Dist: onnx>=1.15.0
Requires-Dist: onnxruntime>=1.16.0
Requires-Dist: skl2onnx>=1.15.0
Requires-Dist: onnxmltools>=1.12.0
Requires-Dist: pandera>=0.17.0
Requires-Dist: category-encoders>=2.6.0
Dynamic: license-file
